invenio_subjects_cessda/__init__.py
invenio_subjects_cessda/config.py
invenio_subjects_cessda/convert.py
invenio_subjects_cessda/fetch_voc.py
invenio_subjects_cessda/schemas.py
invenio_subjects_cessda/utils.py
invenio_subjects_cessda/writer.py
invenio_subjects_cessda/vocabularies/__init__.py
invenio_subjects_cessda/vocabularies/cessda_voc.yaml
invenio_subjects_cessda/vocabularies/vocabularies.yaml
invenio_subjects_cessda-2.0.0.dist-info/METADATA
invenio_subjects_cessda-2.0.0.dist-info/WHEEL
invenio_subjects_cessda-2.0.0.dist-info/entry_points.txt
invenio_subjects_cessda-2.0.0.dist-info/RECORD
