Metadata-Version: 2.4
Name: invenio-subjects-cessda
Version: 2.0.0
Summary: CESSDA subject vocabularies for InvenioRDM.
Project-URL: Homepage, https://github.com/Samk13/invenio-subjects-cessda
Project-URL: Repository, https://github.com/Samk13/invenio-subjects-cessda
Project-URL: Issues, https://github.com/Samk13/invenio-subjects-cessda/issues
Author-email: KTH Royal Institute of Technology <info@kth.se>
License: MIT
Keywords: cessda,invenio,vocabularies
Classifier: Intended Audience :: Developers
Classifier: License :: OSI Approved :: MIT License
Classifier: Operating System :: OS Independent
Classifier: Programming Language :: Python
Classifier: Programming Language :: Python :: 3
Classifier: Programming Language :: Python :: 3.9
Classifier: Programming Language :: Python :: 3.10
Classifier: Programming Language :: Python :: 3.11
Classifier: Programming Language :: Python :: 3.12
Classifier: Programming Language :: Python :: 3.13
Requires-Python: >=3.9
Requires-Dist: aiohttp>=3.9.0
Requires-Dist: click>=8.1.7
Requires-Dist: pyyaml>=6.0.1
Provides-Extra: tests
Requires-Dist: pytest-invenio>=2.1.7; extra == 'tests'
Requires-Dist: pytest>=7.0.0; extra == 'tests'
Requires-Dist: ruff>=0.2.0; extra == 'tests'
